[
  {
    "chain": "eth",
    "dao_id": "aave",
    "has_supported_portfolio": true,
    "id": "aave3",
    "is_tvl": false,
    "is_visible_in_defi": null,
    "logo_url": "https://static.debank.com/image/project/logo_url/aave3/54df7839ab09493ba7540ab832590255.png",
    "name": "Aave V3",
    "platform_token_id": null,
    "portfolio_item_list": [
      {
        "asset_dict": {
          "0xc02aaa39b223fe8d0a0e5c4f27ead9083c756cc2": -51746.126410576355,
          "eth": 56201.05986035949
        },
        "asset_token_list": [
          {
            "amount": 56201.05986035949,
            "chain": "eth",
            "decimals": 18,
            "display_symbol": null,
            "id": "eth",
            "is_core": true,
            "is_verified": true,
            "is_wallet": true,
            "logo_url": "https://static.debank.com/image/coin/logo_url/eth/6443cdccced33e204d90cb723c632917.png",
            "name": "ETH",
            "optimized_symbol": "ETH",
            "price": 2052.49,
            "protocol_id": "",
            "symbol": "ETH",
            "time_at": 1483200000
          },
          {
            "amount": -51746.126410576355,
            "chain": "eth",
            "decimals": 18,
            "display_symbol": null,
            "id": "0xc02aaa39b223fe8d0a0e5c4f27ead9083c756cc2",
            "is_core": true,
            "is_verified": true,
            "is_wallet": true,
            "logo_url": "https://static.debank.com/image/eth_token/logo_url/0xc02aaa39b223fe8d0a0e5c4f27ead9083c756cc2/61844453e63cf81301f845d7864236f6.png",
            "name": "Wrapped Ether",
            "optimized_symbol": "WETH",
            "price": 2052.98,
            "protocol_id": "weth",
            "symbol": "WETH",
            "time_at": 1513077455
          }
        ],
        "detail": {
          "borrow_token_list": [
            {
              "amount": 51746.126410576355,
              "chain": "eth",
              "decimals": 18,
              "display_symbol": null,
              "id": "0xc02aaa39b223fe8d0a0e5c4f27ead9083c756cc2",
              "is_core": true,
              "is_verified": true,
              "is_wallet": true,
              "logo_url": "https://static.debank.com/image/eth_token/logo_url/0xc02aaa39b223fe8d0a0e5c4f27ead9083c756cc2/61844453e63cf81301f845d7864236f6.png",
              "name": "Wrapped Ether",
              "optimized_symbol": "WETH",
              "price": 2052.98,
              "protocol_id": "weth",
              "symbol": "WETH",
              "time_at": 1513077455
            }
          ],
          "health_rate": 1.031787508955946,
          "supply_token_list": [
            {
              "amount": 56201.05986035949,
              "chain": "eth",
              "decimals": 18,
              "display_symbol": null,
              "id": "eth",
              "is_core": true,
              "is_verified": true,
              "is_wallet": true,
              "logo_url": "https://static.debank.com/image/coin/logo_url/eth/6443cdccced33e204d90cb723c632917.png",
              "name": "ETH",
              "optimized_symbol": "ETH",
              "price": 2052.49,
              "protocol_id": "",
              "symbol": "ETH",
              "time_at": 1483200000
            }
          ]
        },
        "detail_types": ["lending"],
        "name": "Lending",
        "pool": {
          "adapter_id": "aave3_proxy_lending",
          "chain": "eth",
          "controller": "0x87870bca3f3fd6335c3f4ce8392d69350b4fa4e2",
          "id": "0x87870bca3f3fd6335c3f4ce8392d69350b4fa4e2",
          "index": null,
          "project_id": "aave3",
          "time_at": 1672325495
        },
        "proxy_detail": {},
        "stats": {
          "asset_usd_value": 115352113.35278924,
          "debt_usd_value": 106233762.59838505,
          "net_usd_value": 9118350.754404187
        },
        "update_at": 1773128761,
        "withdraw_actions": []
      }
    ],
    "site_url": "https://app.aave.com",
    "tag_ids": ["debt"],
    "tvl": 21852323897.660534
  }
]
